{
    "controllerTemplateInfoMapping": {
        "desktopweb": {
            "CopyFBoxDemandRequest0baf5ada8ae3645Controller_desktop": [
                "CopyFBoxDemandRequest0baf5ada8ae3645Controller"
            ],
            "CopyFBoxDemandRequest0c2c1c51673ed4dController_desktop": [
                "CopyFBoxDemandRequest0c2c1c51673ed4dController"
            ],
            "CopyFBoxProductline0b4828ae3534343Controller_desktop": [
                "CopyFBoxProductline0b4828ae3534343Controller"
            ],
            "CopyFBoxProductline0cfaf586391c248Controller_desktop": [
                "CopyFBoxProductline0cfaf586391c248Controller"
            ],
            "CopyFBoxProductline0g693a35b70844aController_desktop": [
                "CopyFBoxProductline0g693a35b70844aController"
            ],
            "CopyFBoxProductline0he56704eefde49Controller_desktop": [
                "CopyFBoxProductline0he56704eefde49Controller"
            ],
            "CopyFlex0ff43866586004cController_desktop": [
                "CopyFlex0ff43866586004cController"
            ],
            "Flex0f834108d4cc042Controller_desktop": [
                "Flex0f834108d4cc042Controller"
            ],
            "flxSampleRowTemplateController_desktop": [
                "flxSampleRowTemplateController"
            ],
            "flxSectionHeaderTemplateController_desktop": [
                "flxSectionHeaderTemplateController"
            ],
            "myflxSegRowWithImageAndLabelController_desktop": [
                "myflxSegRowWithImageAndLabelController"
            ]
        }
    },
    "controllerformInfoMapping": {
        "desktopweb": {
            "DemandRequestFrmController_desktop": [
                "DemandRequestFrmController"
            ],
            "Form1Controller_desktop": [
                "Form1Controller"
            ],
            "ProductLinefrmController_desktop": [
                "ProductLinefrmController"
            ],
            "SKUDemandController_desktop": [
                "SKUDemandController"
            ]
        }
    },
    "formControllerInfoMapping": {
        "desktopweb": {
            "DemandRequestFrm": {
                "controllerActionDir": "DemandRequestFrmController",
                "controllerChannel": "desktop",
                "controllerName": "DemandRequestFrmController"
            },
            "Form1": {
                "controllerActionDir": "Form1Controller",
                "controllerChannel": "desktop",
                "controllerName": "Form1Controller"
            },
            "ProductLinefrm": {
                "controllerActionDir": "ProductLinefrmController",
                "controllerChannel": "desktop",
                "controllerName": "ProductLinefrmController"
            },
            "SKUDemand": {
                "controllerActionDir": "SKUDemandController",
                "controllerChannel": "desktop",
                "controllerName": "SKUDemandController"
            }
        }
    },
    "formsifcMapping": {
        "desktopweb": {
            "DemandRequestFrm": {
                "ControllerExtensions": [],
                "appName": "SKU2",
                "controllerInfo": {
                    "controllerActionName": "DemandRequestFrmController",
                    "controllerChannel": "desktop",
                    "controllerName": "DemandRequestFrmController"
                },
                "enableModelDriven": false,
                "friendlyName": "DemandRequestFrm",
                "isMDAForm": false
            },
            "Form1": {
                "ControllerExtensions": [],
                "appName": "SKU2",
                "controllerInfo": {
                    "controllerActionName": "Form1Controller",
                    "controllerChannel": "desktop",
                    "controllerName": "Form1Controller"
                },
                "enableModelDriven": false,
                "friendlyName": "Form1",
                "isMDAForm": false
            },
            "ProductLinefrm": {
                "ControllerExtensions": [],
                "appName": "SKU2",
                "controllerInfo": {
                    "controllerActionName": "ProductLinefrmController",
                    "controllerChannel": "desktop",
                    "controllerName": "ProductLinefrmController"
                },
                "enableModelDriven": false,
                "friendlyName": "ProductLinefrm",
                "isMDAForm": false
            },
            "SKUDemand": {
                "ControllerExtensions": [],
                "appName": "SKU2",
                "controllerInfo": {
                    "controllerActionName": "SKUDemandController",
                    "controllerChannel": "desktop",
                    "controllerName": "SKUDemandController"
                },
                "enableModelDriven": false,
                "friendlyName": "SKUDemand",
                "isMDAForm": false
            }
        }
    },
    "templateControllerInfoMapping": {
        "desktopweb": {
            "CopyFBoxDemandRequest0baf5ada8ae3645": {
                "controllerActionDir": "CopyFBoxDemandRequest0baf5ada8ae3645Controller",
                "controllerChannel": "desktop",
                "controllerName": "CopyFBoxDemandRequest0baf5ada8ae3645Controller"
            },
            "CopyFBoxDemandRequest0c2c1c51673ed4d": {
                "controllerActionDir": "CopyFBoxDemandRequest0c2c1c51673ed4dController",
                "controllerChannel": "desktop",
                "controllerName": "CopyFBoxDemandRequest0c2c1c51673ed4dController"
            },
            "CopyFBoxProductline0b4828ae3534343": {
                "controllerActionDir": "CopyFBoxProductline0b4828ae3534343Controller",
                "controllerChannel": "desktop",
                "controllerName": "CopyFBoxProductline0b4828ae3534343Controller"
            },
            "CopyFBoxProductline0cfaf586391c248": {
                "controllerActionDir": "CopyFBoxProductline0cfaf586391c248Controller",
                "controllerChannel": "desktop",
                "controllerName": "CopyFBoxProductline0cfaf586391c248Controller"
            },
            "CopyFBoxProductline0g693a35b70844a": {
                "controllerActionDir": "CopyFBoxProductline0g693a35b70844aController",
                "controllerChannel": "desktop",
                "controllerName": "CopyFBoxProductline0g693a35b70844aController"
            },
            "CopyFBoxProductline0he56704eefde49": {
                "controllerActionDir": "CopyFBoxProductline0he56704eefde49Controller",
                "controllerChannel": "desktop",
                "controllerName": "CopyFBoxProductline0he56704eefde49Controller"
            },
            "SampleRowTemplate": {
                "controllerActionDir": "flxSampleRowTemplateController",
                "controllerChannel": "desktop",
                "controllerName": "flxSampleRowTemplateController"
            },
            "SampleSectionHeaderTemplate": {
                "controllerActionDir": "flxSectionHeaderTemplateController",
                "controllerChannel": "desktop",
                "controllerName": "flxSectionHeaderTemplateController"
            },
            "TempDemandRequest": {
                "controllerActionDir": "Flex0f834108d4cc042Controller",
                "controllerChannel": "desktop",
                "controllerName": "Flex0f834108d4cc042Controller"
            },
            "TempSKUDemand": {
                "controllerActionDir": "CopyFlex0ff43866586004cController",
                "controllerChannel": "desktop",
                "controllerName": "CopyFlex0ff43866586004cController"
            },
            "mytplSegRowWithImageAndLabel": {
                "controllerActionDir": "myflxSegRowWithImageAndLabelController",
                "controllerChannel": "desktop",
                "controllerName": "myflxSegRowWithImageAndLabelController"
            }
        }
    },
    "templatesifcMapping": {
        "desktopweb": {
            "CopyFlex0ff43866586004c": {
                "appName": "SKU2",
                "controllerInfo": {
                    "controllerActionName": "CopyFlex0ff43866586004cController",
                    "controllerChannel": "desktop",
                    "controllerName": "CopyFlex0ff43866586004cController"
                },
                "friendlyName": "CopyFlex0ff43866586004c",
                "templateId": "CopyFlex0ff43866586004c"
            },
            "Flex0f834108d4cc042": {
                "appName": "SKU2",
                "controllerInfo": {
                    "controllerActionName": "Flex0f834108d4cc042Controller",
                    "controllerChannel": "desktop",
                    "controllerName": "Flex0f834108d4cc042Controller"
                },
                "friendlyName": "Flex0f834108d4cc042",
                "templateId": "Flex0f834108d4cc042"
            },
            "flxSampleRowTemplate": {
                "appName": "SKU2",
                "controllerInfo": {
                    "controllerActionName": "flxSampleRowTemplateController",
                    "controllerChannel": "desktop",
                    "controllerName": "flxSampleRowTemplateController"
                },
                "friendlyName": "flxSampleRowTemplate",
                "templateId": "flxSampleRowTemplate"
            },
            "flxSectionHeaderTemplate": {
                "appName": "SKU2",
                "controllerInfo": {
                    "controllerActionName": "flxSectionHeaderTemplateController",
                    "controllerChannel": "desktop",
                    "controllerName": "flxSectionHeaderTemplateController"
                },
                "friendlyName": "flxSectionHeaderTemplate",
                "templateId": "flxSectionHeaderTemplate"
            },
            "myflxSegRowWithImageAndLabel": {
                "appName": "SKU2",
                "controllerInfo": {
                    "controllerActionName": "myflxSegRowWithImageAndLabelController",
                    "controllerChannel": "desktop",
                    "controllerName": "myflxSegRowWithImageAndLabelController"
                },
                "friendlyName": "myflxSegRowWithImageAndLabel",
                "templateId": "myflxSegRowWithImageAndLabel"
            }
        }
    },
    "userwidgetsifcMapping": {
        "com.hclsoftwareu.hamburgermenu": {
            "appName": "SKU2",
            "classname": "hamburgermenu",
            "namespace": "com.hclsoftwareu"
        },
        "com.konymp.linechart": {
            "appName": "SKU2",
            "classname": "linechart",
            "namespace": "com.konymp"
        },
        "com.konymp.piechart": {
            "appName": "SKU2",
            "classname": "piechart",
            "namespace": "com.konymp"
        },
        "com.konymp.verticalbar": {
            "appName": "SKU2",
            "classname": "verticalbar",
            "namespace": "com.konymp"
        },
        "com.voltmxmp.multiseriesverticalbar": {
            "appName": "SKU2",
            "classname": "multiseriesverticalbar",
            "namespace": "com.voltmxmp"
        }
    }
}